pysparkhelper/__init__.py
pysparkhelper/pysparkhelper.py
pysparkhelper-0.0.1.dist-info/METADATA
pysparkhelper-0.0.1.dist-info/WHEEL
pysparkhelper-0.0.1.dist-info/top_level.txt
pysparkhelper-0.0.1.dist-info/RECORD
