Metadata-Version: 2.1
Name: pysparkhelper
Version: 0.0.1
Requires-Dist: logclshelper
